odsparsator/.DS_Store
odsparsator/__init__.py
odsparsator/cli.py
odsparsator/odsparsator.py
odsparsator-1.14.0.dist-info/WHEEL
odsparsator-1.14.0.dist-info/entry_points.txt
odsparsator-1.14.0.dist-info/METADATA
odsparsator-1.14.0.dist-info/RECORD
