Metadata-Version: 2.4
Name: odsparsator
Version: 1.14.0
Summary: Generate a json file from an OpenDocument Format .ods file
Keywords: openDocument,ODF,ods,json,spreadsheet,parser
Author: Jérôme Dumonteil
Author-email: Jérôme Dumonteil <jerome.dumonteil@gmail.com>
License-Expression: MIT
Classifier: Development Status :: 5 - Production/Stable
Classifier: Environment :: Console
Classifier: Intended Audience :: Developers
Classifier: License :: OSI Approved :: MIT License
Classifier: Programming Language :: Python
Classifier: Programming Language :: Python :: 3
Classifier: Programming Language :: Python :: 3 :: Only
Classifier: Programming Language :: Python :: 3.10
Classifier: Programming Language :: Python :: 3.11
Classifier: Programming Language :: Python :: 3.12
Classifier: Programming Language :: Python :: 3.13
Classifier: Programming Language :: Python :: 3.14
Classifier: Operating System :: OS Independent
Classifier: Topic :: Text Processing
Classifier: Topic :: Software Development :: Libraries :: Python Modules
Requires-Dist: odfdo>=3.14.0
Requires-Python: >=3.10, <4
Project-URL: Homepage, https://github.com/jdum/odsparsator
Project-URL: Repository, https://github.com/jdum/odsparsator
